himza_itcollege/__init__.py
himza_itcollege-1.0.dist-info/METADATA
himza_itcollege-1.0.dist-info/WHEEL
himza_itcollege-1.0.dist-info/top_level.txt
himza_itcollege-1.0.dist-info/RECORD
