Metadata-Version: 2.1
Name: himza-itcollege
Version: 1.0
Summary: Module for creating an email address
Author: DmytroHimzaITCollege
Author-email: dhimza2020@itcollege.lviv.ua
Classifier: Programming Language :: Python :: 3
Classifier: License :: OSI Approved :: MIT License
Classifier: Operating System :: OS Independent
Requires-Python: >=3.6
